[
    {
        "employer": "Olima",
        "title": "Младший аналитик (IT)",
        "url": "https://api.hh.ru/vacancies/92681061?host=hh.ru",
        "salary_from": 100000,
        "salary_to": 140000,
        "requirement": "Опыт работы в данной сфере необязателен. Перед трудоустройством проводится подготовка. Приветствуются базовые знания SQL, Java, <highlighttext>Python</highlighttext>, C#, JavaScript, PHP."
    },
    {
        "employer": "Olima",
        "title": "Младший аналитик (IT)",
        "url": "https://api.hh.ru/vacancies/92681060?host=hh.ru",
        "salary_from": 100000,
        "salary_to": 140000,
        "requirement": "Опыт работы в данной сфере необязателен. Перед трудоустройством проводится подготовка. Приветствуются базовые знания SQL, Java, <highlighttext>Python</highlighttext>, C#, JavaScript, PHP."
    },
    {
        "employer": "МАСТ",
        "title": "Младший разработчик Python",
        "url": "https://api.hh.ru/vacancies/92706286?host=hh.ru",
        "salary_from": 80000,
        "salary_to": 130000,
        "requirement": "Знание языка <highlighttext>Python</highlighttext>. Знание SQL запросов. Умение работать с следующими библиотеками <highlighttext>Python</highlighttext>: requests, pyqt6, Flask, FastApi, sqlite3, pyinstaller..."
    },
    {
        "employer": "OptimumPrice.ru",
        "title": "Стажер-программист Python (web-parsing)",
        "url": "https://api.hh.ru/vacancies/92532321?host=hh.ru",
        "salary_from": null,
        "salary_to": 30000,
        "requirement": "1. Знание языка программирования <highlighttext>Python</highlighttext>. 2. Опыт работы с фреймворком Scrapy или другими инструментами для парсинга данных. 3. "
    },
    {
        "employer": "Ляхов Сергей",
        "title": "Программист Python",
        "url": "https://api.hh.ru/vacancies/92751436?host=hh.ru",
        "salary_from": 30000,
        "salary_to": 60000,
        "requirement": "Знание <highlighttext>Python</highlighttext>, Git, Google Sheets, Excel. Умение работать в команде. Умение оценивать задачи и укладываться в срок. Умение разбираться в..."
    },
    {
        "employer": "СТЕЛЛА",
        "title": "Frontend разработчик junior",
        "url": "https://api.hh.ru/vacancies/92671339?host=hh.ru",
        "salary_from": 60000,
        "salary_to": null,
        "requirement": "Разбираешься в технологиях построения сайтов и мобильных приложений. Владеешь языками программирования PHP, HTML, CSS, JavaScript, <highlighttext>Python</highlighttext>. Умеешь работать в режиме..."
    },
    {
        "employer": "Лайф Хелп",
        "title": "Программист-разработчик",
        "url": "https://api.hh.ru/vacancies/91568012?host=hh.ru",
        "salary_from": 50000,
        "salary_to": 75000,
        "requirement": "Высшее образование в области IT или смежных дисциплин. - Аналитический склад ума и внимание к деталям. - Наличие компьютера или ноутбука для..."
    },
    {
        "employer": "Мальгин Никита",
        "title": "Junior Backend Developer",
        "url": "https://api.hh.ru/vacancies/91666161?host=hh.ru",
        "salary_from": 30000,
        "salary_to": null,
        "requirement": "Знание <highlighttext>Python</highlighttext>, Django, Django REST Framework. Плюсом будет знание Docker и ngnix."
    },
    {
        "employer": "Блюменкрафт",
        "title": "Программист Python",
        "url": "https://api.hh.ru/vacancies/92617402?host=hh.ru",
        "salary_from": 80000,
        "salary_to": 120000,
        "requirement": "Backend: <highlighttext>Python</highlighttext> 3.7, pymongo, flask, pycades (CryptoPro), aiohttp. Database: MongoDB. Infrastructure: Ansible. ​​​​​​​Знание <highlighttext>Python</highlighttext>, опыт работы с реальными задачами. "
    },
    {
        "employer": "АпТрейдер (UpTrader)",
        "title": "Junior Python Backend Developer",
        "url": "https://api.hh.ru/vacancies/92471522?host=hh.ru",
        "salary_from": null,
        "salary_to": 80000,
        "requirement": "Уверенное знание <highlighttext>python</highlighttext>. Уверенное знание django и DRF. Опыт работы с git. Опыт работы с PostgreSQL и умение писать SQL..."
    },
    {
        "employer": "Trend Soft, студия",
        "title": "Junior Java Developer",
        "url": "https://api.hh.ru/vacancies/91463325?host=hh.ru",
        "salary_from": 50000,
        "salary_to": 70000,
        "requirement": "Знание основных шаблонов проектирования. Умение читать чужой код. Знание Spring, Hibernate. Опыт программирования на языках PHP, Ruby или <highlighttext>Python</highlighttext>. Ответственность. "
    },
    {
        "employer": "Ryzen",
        "title": "Стажер-разработчик Python",
        "url": "https://api.hh.ru/vacancies/92363159?host=hh.ru",
        "salary_from": 50000,
        "salary_to": 50000,
        "requirement": "Отличные коммуникативные навыки. Любовь к коду. Быть активным и внедрять эффективные решения."
    },
    {
        "employer": "ЛАБИРИНТ",
        "title": "Junior Python-программист",
        "url": "https://api.hh.ru/vacancies/92151999?host=hh.ru",
        "salary_from": 45000,
        "salary_to": null,
        "requirement": "Базовые знания <highlighttext>Python</highlighttext> (requests, selenium, bs4). Базовые знания SQL на уровне простых запросов. Знание основ HTML."
    },
    {
        "employer": "БК Олимп",
        "title": "QA-инженер",
        "url": "https://api.hh.ru/vacancies/92676936?host=hh.ru",
        "salary_from": 120000,
        "salary_to": null,
        "requirement": "Опыт выполнения кроссбраузерного тестирования. Знание Postman, Swagger, DevTools, БД. Знание <highlighttext>Python</highlighttext> - будет плюсом. Знание Git на базовом уровне - будет преимуществом."
    },
    {
        "employer": "ФГБОУ ВО МГТУ им. Н.Э. Баумана",
        "title": "Разработчик Python backend",
        "url": "https://api.hh.ru/vacancies/92519276?host=hh.ru",
        "salary_from": 100000,
        "salary_to": 180000,
        "requirement": "Опыт разработки сервисов (Flask, Django, SQLAlchemy и др.). Опыт работы с различными хранилищами данных (MySQL, S3, Hadoop, NoSQL(ClickHouse)). "
    },
    {
        "employer": "ПИКАССО",
        "title": "Backend-разработчик (Python)",
        "url": "https://api.hh.ru/vacancies/92454497?host=hh.ru",
        "salary_from": 70000,
        "salary_to": null,
        "requirement": "Знание Django и умение применять базовые алгоритмы. Опыт работы с базами данных (MySQL, PostgreSQL). Будет хорошо, если вы использовали NoSQL. "
    },
    {
        "employer": "e-Comet",
        "title": "Junior Backend Developer (Python и SQL)",
        "url": "https://api.hh.ru/vacancies/92551827?host=hh.ru",
        "salary_from": 50000,
        "salary_to": 70000,
        "requirement": "Высшее образование (можно неоконченное/неполное) технического ВУЗа последнего или предпоследнего курса. Логичный и структурированный подход к решению задач, способность аргументированно..."
    },
    {
        "employer": "JetLend",
        "title": "Аналитик",
        "url": "https://api.hh.ru/vacancies/92572337?host=hh.ru",
        "salary_from": null,
        "salary_to": 100000,
        "requirement": "Знания <highlighttext>Python</highlighttext> и основных библиотек анализа данных pandas, numpy. Опыт работы в части самостоятельного получения данных. Понимание SQL-запросов. "
    },
    {
        "employer": "ИКоИ",
        "title": "Разработчик (Python)",
        "url": "https://api.hh.ru/vacancies/92693887?host=hh.ru",
        "salary_from": 130000,
        "salary_to": 150000,
        "requirement": "Уверенное знание ООП и структур данных в <highlighttext>Python</highlighttext>. Понимание принципов работы WEB-Технологий: DNS, Web-Сервер, Ajax. Опыт работы с..."
    },
    {
        "employer": "Опен девелоп",
        "title": "Python web3 разработчик",
        "url": "https://api.hh.ru/vacancies/92712797?host=hh.ru",
        "salary_from": 250000,
        "salary_to": 300000,
        "requirement": "<highlighttext>Python</highlighttext>, django, web3, PostgreSQL. Заниение принципов работы dex. Будет плюсом понимание смарт-контрактов для EVM."
    },
    {
        "employer": "Перекрёсток",
        "title": "Маркетинговый аналитик",
        "url": "https://www.superjob.ru/vakansii/marketingovyj-analitik-47506340.html",
        "salary_from": null,
        "salary_to": null,
        "requirement": "Наши предложения:\n• гибридный формат работы\n• самостоятельность в работе и принятии решений\n• карьерное и профессиональное развитие\n• стабильная заработная плата: оклад + бонус\n• комфортный офис с бесплатной парковкой для сотрудников\n• корпоративный транспорт от м. Волгоградский проспект\n• скидки на товары и услуги более чем 900 компаний-партнёров\n• корпоративные скидки для сотрудников X5 Group\n• страхование жизни и здоровья\n• расширенный полис ДМС со стоматологией\n• корпоративная жизнь с праздниками, подарками и мероприятиями\nНаши ожидания:\n• оценка потенциальной рентабельности от бизнес-проектов и рекламных кампаний\n• прогнозирование объема продаж при разных сценариях рекламного бюджетирования\n• анализ по методу АБ-тестирования\n• подготовка кастомных отчетов, дашбордов в Bi-системах\n• автоматизация маркетинговой отчетности\n• построение сквозной маркетинговой аналитики\n• знание и опыт работы c маркетинговыми метриками, оценкой маркетинговых кампаний, понимание моделей атрибуции"
    },
    {
        "employer": "Группа Полюс",
        "title": "Аналитик",
        "url": "https://spb.superjob.ru/vakansii/analitik-47453001.html",
        "salary_from": null,
        "salary_to": null,
        "requirement": "Обязанности:\n• Ежедневный анализ производственных сводок, выявление отклонений и подготовка графиков, зависимостей и их описания.\n• Анализ материалов, рассматриваемых на тендерных комитетах в части потребности и наличия бюджетов, проверка моделей закупа, подготовка заключений по каждой закупке в\nрамках операционной деятельности.\n• Проведение анализа норм потребления нормируемых материалов на регулярной основе, выявления отклонений и их причин, построение графиков и подготовка описания.\n• Участие в бюджетной кампании в части анализа норм потребления нормируемых материалов и ремонтов. Подготовка сравнительного анализа норм предыдущего года к текущему, выявление событий повлиявших на изменение норм в бюджет.\n• Проведение анализа целесообразности аутсорсинга услуг: подготовка финансовых моделей, включая NPV, IRR, PP, DPP для определения эффективности использования\nаутсорсинга против хозяйственного способа.\n• Проведение внутреннего и внешнего бенчмаркинга производственных процессов и\nпоказателей, подготовка сравнительного анализа.\n• Подготовка информации по разовым запросам/запросам государственных органов.\n• Подготовка предложений по совершенствованию автоматизации процессов отдела\n• Подготовка презентационных материалов.\nТребования:\n• Высшее финансовое/экономическое/математическое/техническое образование\n• Опыт работы по направлению деятельности от 1 год\n• \nЗнание программы и инструментов для обработки и анализа данных: продвинутый пользователь Excel, приветствуются знания SQL,PBI, python\nУсловия:\n• Работа в условиях Крайнего Севера на территории Республики Саха (Якутия) по графику работы 5-дневная; Продолжительность рабочего дня: 8 ч.\n• Проживание в пгт. Нижний Куранах, поселок имеет развитую инфраструктуру (больничный комплекс, школу, гимназию, детские сады, магазины, спортивный комплекс, дом культуры). Компенсация аренды жилья. Комплексный обед.\n• Производится оплата проезда к месту отпуска согласно установленного лимита.\n• Возможно предоставление путевок на санаторно-курортное лечение.\n• Спецодежда выдается согласно утвержденным нормам расхода.\nТип занятости:\n\n• Полная занятость"
    },
    {
        "employer": "Сбербанк России",
        "title": "Начальник сектора",
        "url": "https://samara.superjob.ru/vakansii/nachalnik-sektora-48029149.html",
        "salary_from": null,
        "salary_to": null,
        "requirement": "Мы ищем в команду человека, который:\n• Умеет оптимизировать процесс\n• Разбирается в тонкостях аналитики\n• Умеет проводить исследования по эффективности работы сотрудников\n• Понимает в принципах разработки\n• Знает что такое СУБД и Jira\n• Умеет оптимизировать данные\n• Настойчив в достижении целей\n• Любит запускать новые проекты\n• Умеет сплотить и вдохновить команду\nОбязанности\nСектор выполняет следующие задачи:\n• 1. Формирование отчетности и анализ данных\n• подготовка периодической и отчётности по запросу\n• проведение анализов по операционным показателям\n• разработка Dashboard на QlickSense\n• 2. Запуск пилотных проектов\n• выбор сотрудников для пилотов\n• оценка влияния пилота\n• оценка тиражирования пилота\n• 3. Автоматизация процессов отчётности\n• ведение баз данных\n• разработка технических решений на python, web\n• внедрение разработок\n• поддержание и доработка технических решений\n• В секторе 22 человека.\nЗадачи начальника сектора:\n• Выполняет административное и оперативное руководство сектором\n• Отвечает за выполнение показателей сервиса, своевременную и качественную подготовку аналитической отчетности по показателям работы\n• Отвечает за качество данных в Dashboard\n• Отвечает за сопровождение внедряемых проектов по направлениям: сопровождение инсталляции нового программного обеспечения, организация и внесения изменений в системы отчетности\n• Взаимодействие с внутренними клиентами\nТребования\n• Высшее образование\n• Опыт руководства командой аналитиков не менее 10 человек более 1 года\n• Знание организацией СУБД, sql\n• Знание основ прогнозирования и оптимизации процессов\n• Знание принципов построение отчётности и разработки\n• Коммуникабельность\nУсловия\n• Официальное трудоустройство\n• Полный социальный пакет\n• ДМС с первого дня\n• Льготное кредитование\n• Насыщенная корпоративная жизнь\n• Бесплатный тренажерный зал."
    },
    {
        "employer": "SuperJob",
        "title": "Продуктовый аналитик",
        "url": "https://www.superjob.ru/vakansii/produktovyj-analitik-48295049.html",
        "salary_from": null,
        "salary_to": null,
        "requirement": "Вам предстоит:\n• Проверять и генерировать гипотезы в плотной связке с менеджерами продукта.\n• Делать мониторинг основных метрик продукта: дашборды и алертинг.\n\n• Если произойдет значимое изменение метрики продукта, вместе с менеджерами продукта искать причины изменений. \n• Выстраивать совместную эффективную работу с продуктовым юнитом. \n• Тестировать гипотезы по улучшению метрик, проводить А/Б тесты и интерпретировать их результаты.\n• Проектировать разметку событий аналитики.\n• Предоставление аналитической информации по запросам сотрудников компании.\nОт своего будущего коллеги мы ждем:\n• Опыт работы в любой BI-системе (у нас Tableau), Яндекс.Метрике и Excel.\n• Знание SQL: навыки написания сложных запросов, знание оконных функций (у нас ClickHouse).\n• Знание Python и его библиотек (Pandas, NumPy, SciPy). \n• Опыт тестирования продуктовых гипотез (А/Б тесты).\n• Опыт разметки событий аналитики.\nСвоему будущему коллеге мы предлагаем:\n• Работу в одном из самых быстрорастущих рынков - HRTech.\n• Высокую инженерную культуру.\n• Непрерывное обучение и профессиональное развитие внутри компании.\n• Возможность стать частью сплоченной команды, любящей свое дело.\n• Регулярную обратную связь от наставников и руководителей.\n• Официальную заработную плату.\n• ДМС после прохождения испытательного срока.\n• Современный офис в 10 минутах пешей прогулки от станций метро Пушкинская/Маяковская/Чеховская/Новослободская.\n• Спортивный уголок.\n• Комфортную зону отдыха.\n• Кофе-поинты с вкуснейшим кофе и вендинговым аппаратом.\n• Оборудованное просторное место для питания.\n• Оплату проезда общественным транспортом."
    },
    {
        "employer": "Санкт-Петербургский горный университет",
        "title": "Ведущий инженер",
        "url": "https://spb.superjob.ru/vakansii/veduschij-inzhener-46009011.html",
        "salary_from": 60000,
        "salary_to": null,
        "requirement": "В отделе наукометрического анализа Санкт-Петербургского горного университета открыта вакансия \"Ведущий инженер\"\nОбязанности:\n• умение работать в наукометрических базах данных (Scopus, Web of Science, РИНЦ и др.);\n• осуществлять сбор, обработку, интерпретацию и оформление сводно-аналитической информации;\n• подготовку презентационных материалов по вопросам, относящимся к публикационной деятельности. \nТребования:\n• Высшее образование;\n• Уверенное владение Word, Excel и Google документами;\n• Приветствуем наличие опыта в области анализа данных (Python, R, Power Query);\n• Активность, коммуникабельность, доброжелательность;\n• Умение структурировать и выделять главное из большого объема информации;\n• Навыки работы с документами, деловой переписки;\n• Личные качества: ответственность, исполнительская дисциплина, коммуникабельность, обучаемость, умение работать в коллективе, стрессоустойчивость, умение работать в режиме многозадачности, доброжелательность. \nУсловия:\n• Трудоустройство в соответствии с ТК РФ;\n• Заработная плата от 60 000 руб. (+ надбавка после прохождения испытательного срока);\n• Испытательный срок 3 месяца;\n• График работы: пятидневка, Пн.-Чт. с 8.30 до 17.15, Пт. с 8.30 до 16.15;"
    },
    {
        "employer": "\"Всероссийский научно-исследовательский институт авиационных материалов\" Национального исследовательского центра \"Курчатовский институт\"",
        "title": "Инженер (трансфер технологий)",
        "url": "https://www.superjob.ru/vakansii/inzhener-47454519.html",
        "salary_from": 60000,
        "salary_to": 100000,
        "requirement": "Обязанности:\n• участие в работах по развитию центра трансфера технологий с применением информационных технологий;\n• создание и управление базами данных по управлению результатами интеллектуальной деятельности;\n• проведение экспертиз отчетной документации и результатов научно-технической деятельности, полученных в рамках НИР, ОТР и ОКР в целях выявления охраноспособных результатов работ и готовить рекомендаций по их правовой охране;\n• участие в информационно-аналитической и технической помощи научным подразделениям института при планировании и выполнении ими научно-исследовательских работ;\n• построение патентных ландшафтов в сфере деятельности Предприятия;\n• участие в работе по обеспечению, с использованием новых информационных технологий, подразделений института и руководства института специально подготовленной информацией с целью повышения научно-технических знаний сотрудников и создания внешней и внутренней информационной среды предприятия.\nТребования:\n• высшее образование: инженерно-техническое или в области информационно-телекоммуникационных технологий;\n• уверенный пользователь ПК;\n• уверенный пользователь Excel, Word, Power Point, Access, 1С;\n• знание языков программирования (Python, SQL, и др.);\n• навыки работы по разработке технического задания для создания баз данных и программного обеспечения;\n• навыки работы с наполнением и управлением баз данных;\n• навыки статистической обработки данных;\n• хорошие аналитические способности;\n• английский язык - не ниже среднего уровня.\nУсловия:\n• Ближайшая станция метро: м. Бауманская, м. Курская.\n• График работы: 09.00 - 18.00 (пн.-чт), 09.00 - 16.45 (пт.);\n• Официальное трудоустройство;\n• Детские лагеря;\n• Собственная база отдыха."
    },
    {
        "employer": "Банк ВТБ (ПАО)",
        "title": "Продуктовый web-аналитик (Стрим дебетовые карты и счета)",
        "url": "https://www.superjob.ru/vakansii/produktovyj-web-analitik-47316909.html",
        "salary_from": null,
        "salary_to": null,
        "requirement": "Обязанности:\n• настройка системы сбора, процессов и методов по сбору данных;\n• настройка новых отчетов из Яндекс.Метрики;\n• настройка метрик на сайтах и посадочных страницах;\n• проверка данных на достоверность в системах аналитики при формировании еженедельных/ежедневных отчетов в системе Яндекс.Метрика;\n• проведение анализа результативности всех каналов трафика;\n• проведение анализа количественных и качественных показателей трафика на веб-сайте;\n• мониторинг поведенческих характеристик пользователей при посещении веб-сайта;\n• участие в подготовке тех.заданий на новые лендинги компании;\n• подготовка регулярного отчета по сайту и лендингам;\n• подготовка отчетов в различных срезах (по страницам, по городам, по продуктам, по аудитории, по конверсиям, по событиям, выстраивание воронки);\n• анализ данных и подготовка рекомендаций для команды маркетинга.\nТребования:\n• опыт работы не менее 2-х лет в банке/агентстве работающем с банками;\n• обязательное владение SQL на уровне сложных запросов;\n• опыт работы с системами визуализации данных PowerBI / Google Data Studio и т.д.;\n• визуализация данных с помощью дашбордов;\n• умение работать с большим массивом данных;\n• желательно знание Python;\n• свободное владение основными инструментами веб-аналитики (Яндекс Метрика, Google Analytics);\n• логика и cтратегическое мышление."
    },
    {
        "employer": "ТБ ПРОЕКТ",
        "title": "Системный администратор",
        "url": "https://www.superjob.ru/vakansii/sistemnyj-administrator-45760672.html",
        "salary_from": null,
        "salary_to": 150000,
        "requirement": "Обязанности:\n• Поддержание рабочего состояния рабочих станций\n• Поддержка пользователей (включая удаленную)\n• Участие в развитии внутренней инфраструктуры, её техническое сопровождение\nТребования:\n• Понимание основ сети (TCP/IP, DNS, VPN, VLAN, DHCP)\n• Навыки работы с Windows Server – TS, AD, GPO, WSUS, Hyper-V\n• Минимальный опыт администрирования БД MSSQL\n• Базовые навыки администрирования Windows и *nix\n• Настройка базового бухгалтерского ПО – CryptoPro, контур, такском, 1C\nЖелательно:\n• Zabbix\n• FreePBX/Asterisk\n• Cisco ASA, Juniper EX\n• nix: bash, exim4, dovecot, nginx, php-fpm, gunicorn\n• Знание python на минимальном уровне\nС чем предстоит работать:\n• Кластер на базе Hyper-V\n• MS инфраструктура включая SCCM, DPM, MSSQL.\n• Сетевое оборудование Cisco ASA, Juniper EX, Ubiquity\n• IP телефония на базе FreePBX\n• Более 100 пользователей\n• Несколько офисов на территории г. Москва и ближайшее Подмосковье.\n• 98% времени работа в офисе по адресу Амундсена, 9, но редкие выезды в другие офисы будут\nУсловия:\n• формление по ТК РФ;\n• официальная з/п\n• график работы 5/2;\n• шаговая доступность от метро Свиблово (7 мин).\n• полный рабочий день (с 9.00 до 18.00)\n• на территории работодателя"
    },
    {
        "employer": "Кадровый Центр Департамента здравоохранения города Москвы",
        "title": "Аналитик данных",
        "url": "https://www.superjob.ru/vakansii/analitik-dannyh-48443951.html",
        "salary_from": 100000,
        "salary_to": null,
        "requirement": "Обязанности: \n• Анализ данных по заданным критериям\n \n• Построение отчетности на основании анализа и создание визуального ряда по итогу работы (таблицы, графики, диаграммы, презентационные материалы)\n \n• Умение создавать дашборды и работать с ними\n \nТребования: \n• Высшее образование, наличие сертификатов об обучении, связанных с аналитикой данных\n \n• Опыт работы не менее 1 года по данной специальности\n \n• Очень высокий уровень владения Excel, Python, Power Point\n \n• Знания SQL, опыт работы в структуре здравоохранения (государственные, частные медицинские организации, фармацевтические организации) – будет преимуществом для кандидата\n \n• Работа в команде, гибкость, лояльное отношение к рабочему процессу\n \nУсловия:\n \n• Работа в государственном учреждении\n \n• График работы с 09:00 до 18:00, лояльное отношение к рабочему процессу (возможность задержаться на 1 час)\n \n• Оформление по ТК РФ\n \n• Адрес места работы: г. Москва, Смоленский бульвар, д. 24 стр. 4 (периодически возможна дистанционная работа)"
    },
    {
        "employer": "Образовательный холдинг СИНЕРГИЯ",
        "title": "Преподаватель ИТ дисциплин",
        "url": "https://www.superjob.ru/vakansii/prepodavatel-it-disciplin-48570280.html",
        "salary_from": 150000,
        "salary_to": 150000,
        "requirement": "Обязанности:\nПроводить обучение обучающихся в соответствии с требованиями федеральных государственных образовательных стандартов по дисциплинам:\n• Базы данных\n• Управление данными\n• Стек технологий Python\n• Основы разработки веб-сервисов\nТребования:\n• Наличие учёной степени и учёного звания обязательно.\n• Опыт работы со студентами высшей школы и СПО, убедительные навыки методической работы.\nУсловия:\n• Оформление в соответствии с ТК РФ.\n• Полная занятость 5/2 с 09.00 до 18.00.\n• По договору ГПХ и по совместительству не рассматриваем."
    },
    {
        "employer": "КНИРТИ",
        "title": "Специалист по информационной безопасности",
        "url": "https://obninsk.superjob.ru/vakansii/specialist-po-informacionnoj-bezopasnosti-47702106.html",
        "salary_from": 60000,
        "salary_to": 70000,
        "requirement": "Обязанности:\n• Настройка и управление подсистемами безопасности;\n• Настройка и управление коммутационным оборудованием;\n• Управление инфраструктурой управления доступами;\n• Анализ журналов событий;\n• Анализ инцидентов ИБ, участие в их расследовании;\n• Проведение аудитов информационной безопасности.\nТребования:\n• Высшее профессиональное (техническое) образование;\n• Windows и Linux на уровне администратора;\n• Базовые знания работы сетей;\n• Знание принципов работы служб каталогов (AD, LDAP);\n• Понимание принципов сетевой и компьютерной безопасности;\n• Опыт автоматизации (bash, perl, python);\n• Знание законодательной базы обеспечения ИБ;\n• Коммуникабельность, ответственность, обучаемость.\nУсловия:\n• официальное трудоустройство согласно ТК РФ;\n• работа на ведущем научно-производственном предприятии;\n• график работы 5/2 с 8.00 до 17.00;\n• стабильная заработная плата, социальный пакет;\n• адаптация на месте, отличные наставники, поддерживающий коллектив;\n• возможность профессионального роста и развития;\n• возможность обучения за счет средств предприятия;\n• на предприятии находится медицинский пункт, после прохождения испытательного срока, есть возможность прохождения основных врачей, включая стоматологию;\n• спортивный зал на территории предприятия;\n• организация ежегодного отпуска для работников;\n• возможность отдыха в г. Сочи (от 1 года работы на предприятии), с частичной компенсацией;\n• при необходимости предоставляются оплачиваемые дни (свадьба работника, рождение ребенка, поступление ребенка в 1-й класс (родителям в День Знаний);\n• место работы: г. Жуков, ул. Ленина, д.2."
    },
    {
        "employer": "Школа программирования",
        "title": "Учитель по программированию",
        "url": "https://andreevka.superjob.ru/vakansii/uchitel-po-programmirovaniyu-45698480.html",
        "salary_from": null,
        "salary_to": 60000,
        "requirement": "Обязанности:\n• \nОбучение детей (4-14 лет) в группах программированию \n• \nФормирование у учеников логического системного мышления и развитие технических творческих способностей \n\n• Обучение детей основам проектной работы в IT\n• Поддержание интереса и мотивации учеников \nТребования:\n• \nОпыт работы с детьми (аниматор, репетитор, воспитатель, вожатый, учитель, опытный родитель или старший брат/сестра\n• Уверенное владение компьютером. В идеале, знание основ алгоритмического языка и программирования. (Предпочтительно: Scratch JR, Scratch, Snap, Stencyl, Tynker, Blockly, Перволого, Пиктомир)\n• Умение объяснять сложное простыми (иногда детскими) словами \n• Любовь к детям и умение направить их энергию в нужное русло \n\n• Знание текстовых языков программирования Python, Java и прочее - желательно \n\nУсловия:\n• \nУдобный график (очень многое можно скорректировать совместно с администратором) \n• Возможность обучать мотивированных детей, которые стремятся узнать все о современных технологиях и не только \n• Увлеченная команда преподавателей \n\n• Интересные и амбициозные задачи\n• Профессия квалифицированного детского IT тренера - одна из самых востребованных на рынке труда"
    },
    {
        "employer": "Волжский трубный завод",
        "title": "Инженер-программист",
        "url": "https://volzhskiy.superjob.ru/vakansii/inzhener-programmist-47078636.html",
        "salary_from": 50000,
        "salary_to": null,
        "requirement": "В проектный офис программы «Цифровое производство ТМК» требуется инженер-программист.\nЧем Вам предстоит заниматься:\n• Сопровождение программ;\n• Сопровождение баз данных;\nЭта вакансия для Вас, если Вы:\n• Знаете любой из языков программирования (C#/ C++/C/Python);\n• Имеете уровень владения ПК – высокий (среда разработки Visual Studio или её аналоги).\nЧто мы предлагаем:\n• График работы: 5/2;\n• Компенсация питания;\n• Предоставление компенсации за наём жилья;\n• Доставка корпоративным транспортом;\n• Льготные условия ипотеки;\n• Обучение в Корпоративном университете компании, повышение квалификации;\n• Участие в Молодежной Научно-Практической Конференции;\n• Социальный пакет: собственная Медико-Санитарная Часть, скидки на партнерские программы (спортивные залы, бассейн), путевки в оздоровительные учреждения."
    },
    {
        "employer": "Тензор",
        "title": "Инженер MQ",
        "url": "https://kirov-kaluga.superjob.ru/vakansii/inzhener-mq-47097107.html",
        "salary_from": 125000,
        "salary_to": null,
        "requirement": "Систему СБИС придумали, создали и постоянно совершенствуют более 1500 разработчиков в 11 филиалах по стране. У нас есть фанаты дата- майнинга , эксперты в разработке кроссплатформенных приложений и высоконагруженных систем, разработчики мобильных, настольных и веб-приложений, специалисты по обработке, анализу и хранению больших массивов данных.\nЖдем от вас:\n• \nПонимание концепции MQ;\n• \nПонимание принципов масштабируемости, отказоустойчивости и доступности систем;\n• \nЗнание стека протоколов TCP/IP;\n• \nНавыки программирования на скриптовых языках;\n• \nОпыт использования и администрирования Linux , понимание и нахождение узких мест системы, настройка ядра;\n• \nОпыт работы с системами контроля версий.\nЖелательно:\n• \nОпыт работы с RabbitMQ ;\n• \nЗнакомство c Erlang / Python / Lua ;\n• \nЗнакомство с ElasticSearch , GrayLog ;\n• \nЗнакомство с протоколами AMQP/STOMP;\n• \nУчастия в разработке высоконагруженных проектов.\nВам предстоит заниматься:\n• \nРазвитием и поддержкой кластеров MQ на основе RabbitMQ ;\n• \nРазвитием и сопровождением кластеров ElasticSearch .\nМы предлагаем:\n• \nзаработную плату в зависимости от квалификации и уровня ответственности;\n• \nоформление по ТК РФ;\n• \nпремии по итогам работы за месяц;\n• \nДМС, спорт;\n• \nоборудованное место в комфортном офисе или возможность работать из дома в любимых тапочках;\n• \nпомощь опытного наставника на испытательный срок;\n• \nгибкое начало и окончание рабочего дня, свободный дресс -код;\n• \nкорпоративные скидки и бонусы от наших партнеров (обучающие курсы, товары и т.д.);\n• \nподарки от компании при заключении брака и рождении детей;\n• \nсоциальную поддержку при сложных жизненных ситуациях;\n• \nкорпоративную библиотеку.\nА еще у нас один из лучших, современных офисов в городе, в котором располагается собственное кафе с выходом на крышу, лобби-б ар, столовая, современный тренажерный зал."
    },
    {
        "employer": "АНО ДПО ЦЕНТР ОБРАЗОВАНИЯ И ВОСПИТАНИЯ ДЕТЕЙ И МОЛОДЕЖИ",
        "title": "Педагог дополнительного образования (АЭРО квантум)",
        "url": "https://pskov.superjob.ru/vakansii/pedagog-dopolnitelnogo-obrazovaniya-47547702.html",
        "salary_from": 30000,
        "salary_to": null,
        "requirement": "Обязанности:\n• Проведение занятий, ведение документации (заполнение журналов, составление дополнительных образовательных программ),\n• Работа с оборудованием: наборы для сборки квадрокоптеров \"Клевер 3\", ресурсные наборы для сборки квадрокоптеров, квадрокоптеры DJI, тепловизионная и мультиспектральная камеры, паяльные станции. (Обучаем работать с оборудованием),\n• Сопровождение проектной деятельности обучающихся по конструированию и программированию БПЛА,\n• Знания в области проектирования БПЛА, физики, программирования на языке python,\n• Участие в разработке и проведении тематических смен и внеучебных мероприятий. \nТребования:\n• Высшее образование. Желательно педагогическое/техническое или неоконченное высшее (4 курс бакалавриат),\n• Углубленные знания в области строения и программирования БПЛА,\n• Медицинская книжка (желание ее оформить),\n• Высокий уровень компьютерной грамотности,\n• Тактичность,\n• Творческий подход и любознательность. \nУсловия:\n• З/П от 30.00 (при полной занятости),\n• Гибкий график,\n• Премии за интенсивность труда, \n• Молодой и дружный коллектив,\n• Оплачиваемый медицинский осмотр, \n• Современное оборудование для работы. \n• Мы ищем человека, который хочет быть педагогом, имеет навыки работы с детьми и знания в необходимой области. Мы готовы помогать на всех этапах работы — от формирования учебного плана до работы с оборудованием и ведения проектной деятельности. Возможна работа по совместительству."
    },
    {
        "employer": "Школа № 1678 «Восточное Дегунино»",
        "title": "Учитель информатики",
        "url": "https://www.superjob.ru/vakansii/uchitel-informatiki-47820018.html",
        "salary_from": 90000,
        "salary_to": null,
        "requirement": "Обязанности:\n• Осуществляет обучение и воспитание обучающихся с учетом специфики преподаваемого предмета, проводит уроки и другие занятия в соответствии с расписанием в указанных помещениях.\n• Составляет тематический план работы по предмету в каждой параллели классов на учебную четверть и рабочий план на каждый урок.\n• В своей работе по предмету использует разнообразные приемы, методы и средства обучения.\n• Реализует образовательные программы.\n• Может переставлять по своему усмотрению темы уроков в отдельных разделах программы.\n• Проводит с учащимися установленное учебным планом количество контрольных и практических работ, а также необходимые учебные экскурсии.\n• работа в ЭЖД\nТребования:\n• высокий или экспертный уровень ознакомительного тренинга МЦКО в формате ЕГЭ\n• знание языков Paskal, Python\n• желательно наличие опыта подготовки к ГИА"
    },
    {
        "employer": "SuperJob",
        "title": "DevOps-инженер",
        "url": "https://www.superjob.ru/vakansii/devops-inzhener-48366477.html",
        "salary_from": null,
        "salary_to": null,
        "requirement": "Мы ожидаем от кандидата опыт:\n• Опыт DevOps от 3-х лет.\n• Администрирования Linux.\n• Администрирования Kubernetes.\n• Настройки и эксплуатации CI/CD.\n• Эксплуатации и отладки СУБД (MySQL/MariaDB, Postgres, ClickHouse, Redis).\n• Программирования (скрипты Bash/PHP/Python/Go).\n• Настройки и эксплуатации web-проектов.\n• Использования и настройки систем мониторинга.\nЧем предстоит заниматься:\n• Управлять мониторингом zabbix, grafana.\n• Реагировать на инциденты, не теряя присутствия духа.\n• Поддерживать актуальный план восстановления в случае сбоев.\n• Находить узкие места в архитектуре проекта и приложений.\n• Рулить конфигурацией сервисов nginx, mariadb, clickhouse, apache, rabbitmq и других.\n• Писать плейбуки и роли для ansible для конфигурации и деплоя.\n• Контейнеризировать новые сервисы и поддерживать старые.\n• Поддерживать стороннее ПО (sentry, bitbucket, teamcity итд).\n• Рулить процессом continuous integration и deployment.\n• Описывать конфигурацию новых сервисов на Jsonnet.\n• Администрировать Kubernetes.\nМы используем в работе свой дата-центр, пару сотен серверов, CentOs/Virtuozzo, Git, Nginx, Apache, NodeJS, Bash/Sh, PHP, Python, Rust, Go, MariaDB/MySql, PostgreSQL, Redis, Sphinx, RabbitMQ, Memcache, ClickHouse, ELK, Graphite/Grafana, Zabbix, TeamCity, Jenkins, Docker, Kubernetes, Ansible, Nexus, Vault, Atlassian Jira/Confluence/BitBucket. \nСвоему будущему коллеге мы предлагаем:\n• Работу в одном из самых быстрорастущих рынков - HRTech.\n• Высокую инженерную культуру.\n• Непрерывное обучение и профессиональное развитие внутри компании.\n• Возможность стать частью сплоченной команды, любящей свое дело.\n• Регулярную обратную связь от наставников и руководителей.\n• Официальную заработную плату.\n• ДМС после прохождения испытательного срока.\n• Современный офис в 10 минутах пешей прогулки от станций метро Пушкинская/Маяковская/Чеховская/Новослободская.\n• Спортивный уголок.\n• Комфортную зону отдыха.\n• Кофе-поинты с вкуснейшим кофе и вендинговым аппаратом.\n• Оборудованное просторное место для питания.\n• Оплату проезда общественным транспортом."
    },
    {
        "employer": "ЕвроАвто",
        "title": "Web-разработчик (backend)",
        "url": "https://spb.superjob.ru/vakansii/web-razrabotchik-41964533.html",
        "salary_from": 100000,
        "salary_to": null,
        "requirement": "Ищем талантливого Backend разработчика с опытом работы на коммерческих проектах, который станет частью команды разработки портала EuroAuto и других проектов компании.\nИспользуемый стек технологий:\n- PHP 7.4 (Silex, Kohana, Laravel, Symfony);\n- Шаблонизатор Twig;\n- Python;\n- NoSQL: Redis, Memcached;\n- PostgreSQL, MSSQL;\n- CI/CD;\n- Docker/Kubernetes;\n- GitLab/Kibana;\n- JS, TypeScript, ReactJS, jQuery;\n- Bootstrap3/5, Webpack ,SASS/SCSS/CSS.\nЧем предстоит заниматься:\n- Разработка и сопровождение новых фич;\n- Поддержка и рефакторинг ранее разработанного функционала;\n- Решение проблем и оптимизация производительности;\n- Участвовать в проектировании и принятии архитектурных решений;\n- Взаимодействовать с фронт-разработчиками, тестировщиками и бизнесом.\nТребования:\n- Уверенные знания PHP7, опыт веб-разработки не менее 3-х лет;\n- Опыт работы с фреймворками Laravel или Symfony от 1 года;\n- Понимание ООП и паттернов проектирования, умение их применять;\n- Знание SQL на уровне написания запросов средней сложности;\n- Опыт работы с REST API, понимание протокола HTTP;\n- Опыт работы в команде с использованием Git;\n- Умение разбираться в чужом коде.\nПожелания:\n- Опыт создания высоконагруженных проектов;\n- Умение декомпозировать задачи и доводить их до конца;\n- Опыт использования docker для локальной разработки (Nginx+php-fpm);\n- Вы достаточно самостоятельны, чтобы разобраться в устройстве процесса, системы;\n- Вы достаточно внимательны и напишите в сопроводительном письме в какой версии php появилась функция is_countable();\n- Опыт использования PHPUnit.\nПреимущества:\n• Официальное трудоустройство и достойная заработная плата;\n• Гибридный график работы - 3 дня в офисе (понедельник-среда и четверг пятница-удаленная работа), начинаем работу в гибком графике - с 8 до 10;\n• Свободный dress code;\n• Комфортный офис в шаговой доступности от м. Петроградская/Чкаловская;\n• Чай, кофе, печеньки, обеды за счёт компании;\n• Комфортный темп разработки;\n• Возможность обучаться за счёт компании, возможность профессионального роста;\n• Скидка на покупку деталей и ремонт автомобиля в сервисах ЕвроАвто;\n• Корпоративные подарки для детей и взрослых;\n• Корпоративный футбол;\n• Участие в крупном проекте по развитию web – направления сети;\n• Возможность выбора направления работы."
    },
    {
        "employer": "Радиофизика",
        "title": "Инженер-радиоэлектронщик 1 категории",
        "url": "https://www.superjob.ru/vakansii/inzhener-radioelektronschik-1-kategorii-43148990.html",
        "salary_from": 100000,
        "salary_to": null,
        "requirement": "Обязанности:\n\n - участие в проектировании устройств по ТЗ\n- написание программ для микроконтроллеров различных производителей (Atmel, STM32 и др.)\n- написание прикладных программ для ПК\n- разработка и согласование технических заданий и технических условий. \n\nТребования:\n - высшее (техническое) образование\n- знание С++, Python, Java\n- опыт работы с контроллерами Atmel, Cortex\n- приветствуются знания схемотехники, оптоэлектроники, умение паять и т.п. \n\nУсловия:\n- работникам ПАО \"Радиофизика\" предоставляется право на отсрочку от призыва на военную службу по мобилизации;\n- стабильная, официальная заработная плата;\n- периодическая индексация заработной платы;\n- периодический медицинский осмотр;\n- соц. пакет: дополнительное медицинское обслуживание;\n- ст. м. Планерная, ул. Героев Панфиловцев, д. 10 (шаговая доступность от станции метро)."
    },
    {
        "employer": "Банк ВТБ (ПАО)",
        "title": "Продуктовый web-аналитик (Стрим дебетовые карты и счета)",
        "url": "https://www.superjob.ru/vakansii/produktovyj-web-analitik-47176559.html",
        "salary_from": null,
        "salary_to": null,
        "requirement": "Обязанности:\n• выгрузка сырых данных с помощью SQL. Оптимизация SQL запросов для регулярных выгрузок;\n• настройка новых отчетов из Яндекс.Метрики;\n• участие в подготовке ТЗ на новые лендинги компании;\n• настройка метрик на сайтах и посадочных страницах.\n• проверка данных на достоверность в системах аналитики при формировании еженедельных/ежедневных отчетов в системе Яндекс.Метрика.\n• проведение анализа результативности всех каналов трафика;\n• проведение анализа количественных и качественных показателей трафика на веб-сайте;\n• мониторинг поведенческих характеристик пользователей при посещении веб-сайта;\n• подготовка регулярного отчета по сайту и лендингам;\n• подготовка отчетов в различных срезах (по страницам, по городам, по продуктам, по аудитории, по конверсиям, по событиям, выстраивание воронки).\nТребования:\n• опыт работы не менее 2 лет в банке/агентстве работающем с банками;\n• обязательно знание SQL на уровне написания сложных, оптимизированных запросов. Желательно знание Python;\n• опыт работы с системами визуализации данных PowerBI / Google Data Studio и т.д.;\n• свободное владение основными инструментами веб-аналитики – Яндекс Метрика, Google Analytics;\n• умение работать с большим массивом данных."
    }
]